{"doctext": "on 5 november , radio ve ##nce ##rem ##os reports that guerrillas have carried out 2 ambush ##es along the pan ##ame ##rica ##n highway , in ##flict ##ing 26 army casualties . the report indicated that at 06 ##00 on 4 november , the rebels placed a bomb on a light tank near flores de te ##pe ##ya ##c , ap ##ast ##ep ##e ##que . it is estimated that the action resulted in 9 casualties ; the light tank was completely destroyed . the second ambush occurred at 08 ##15 on 4 november . the rebels ambushed a 10 - vehicle military convoy and left at least 17 casualties . some time after the rebel action , the army directed mortar fire to the area and the air force leveled machine ##gun fire upon this populated zone . traffic on the pan ##ame ##rica ##n highway was paralyzed while the armed forces evacuated the many casualties from the area in helicopters . a later report told of urban commandos attacking a treasury police unit at 5th avenue and 5th po ##nie ##nte street in san salvador , resulting in 2 casualties to the treasury police . also , rebel units were said to attack military detachment no 1 commandos on the outskirts of to ##ton ##ique , cha ##late ##nan ##go department during the afternoon of 3 november , in ##flict ##ing two casualties . in another item , the central ana ##sta ##cio aquino front was reported to claim taking part in actions against the bell ##oso battalion . fm ##ln rebels clashed with soldiers in canton co ##yo ##lit ##o in te ##col ##uca jurisdiction , san vicente department at 09 ##00 on 3 november , and inflicted three casualties . that same day , the same unit was attacked in fin ##ca sa ##je ##lio and the guerrillas claimed to have inflicted 2 more casualties . the same troops were said to suffer 2 more casualties in a mined area on 4 november . an fm ##ln unit was also said to have seized the town of los hernandez in canton mata ##san ##o , cab ##ana ##s department on 4 november . four p ##yl ##ons were blown up , interrupting a 46 , 000 - vol ##t electrical line . radio ve ##nce ##rem ##os on 6 november carries its weekly military report : \" during the past week , radio ve ##nce ##rem ##os reported in ##flict ##ing many casualties on the armed forces . the total number of casualties inflicted on the armed forces was 124 , including an arc ##e battalion officer who was hit in ( word ind ##ist ##in ##ct ) . fm ##ln forces ambushed five military convoys along different highways throughout the country . during the week , two paramilitary members were captured . the fm ##ln respected the lives of these men and released them immediately , but confiscated their 3 rifles and 300 cartridges . we highlight the attack by our urban commandos on command staff installations . this attack took place in a san salvador that is totally mil ##ita ##rized , nevertheless , we managed to hit the top death squads members ' central nerve . guerrilla actions in the meta ##pan area increased during the week and our men ambushed soldiers along the santa ana - meta ##pan road several times . in cha ##late ##nan ##go , our men carried out continuous actions against 4th infantry brigade troops in el ref ##ug ##io and other places in san ignacio . we have already amp ##ly reported heavy clashes against paramilitary groups in san francisco canton , cab ##ana ##s department , where we captured the aforementioned prisoners and confiscated their weapons . we carried out important ambush operations against military troops trying to transit the pan ##ame ##rica ##n and coastal highways in san vicente and la paz departments . we also met the bell ##oso battalion troops and caused their first casualties . \" the station also reported that guerrillas attacked a section of the so ##rian ##o battalion in fin ##ca las mercedes and inflicted three casualties on the 1st infantry brigade troops , including a radio operator . an m - 16 rifle was confiscated from the soldiers . rebel unit was said to have ambushed a military convoy along the coastal road near san cr ##isto ##bal in the te ##col ##uca jurisdiction , san vicente department at noon of 5 november . our men confirm having inflicted 6 army casualties .", "pred_seq": "bombing [SEP] guerrillas guerrillas [SEP] [SEP] light tank tank [SEP] [SEP] bomb bomb [SEP] [unused0] bombing [SEP] guerrillas guerrillas [SEP] treasury treasury treasury treasury treasury [SEP] [SEP] [SEP] bomb bomb [SEP] [unused0] [unused0] [unused0] [unused0] [unused0] [unused0] [unused0] [unused0] [unused0] [unused0] [unused0] [unused0] [unused0] [unused0] [unused0] [unused0] [unused0] [unused0] [unused0] [unused0] [unused0] [unused0] [unused0] [unused0] [unused0] [unused0] [unused0] [unused0] [unused0] [unused0] [unused0] [unused0] [unused0] [unused0] [unused0] [unused0] [unused0] [unused0] [unused0] [unused0] [unused0] [unused0] [unused0] [unused0] [CLS]", "pred_templates": [{"incident_type": "bombing", "PerpInd": [["guerrillas"]], "PerpOrg": [], "Target": [["light tank"]], "Victim": [], "Weapon": [["bomb"]]}, {"incident_type": "bombing", "PerpInd": [["guerrillas"]], "PerpOrg": [["treasury"]], "Target": [], "Victim": [], "Weapon": [["bomb"]]}], "gold_templates": [{"incident_type": "attack", "PerpInd": [], "PerpOrg": [["army"], ["air force"]], "Target": [], "Victim": [], "Weapon": [["mortar"], ["machinegun"]]}, {"incident_type": "bombing", "PerpInd": [["unit", "fmln unit"]], "PerpOrg": [["fmln"]], "Target": [["pylons"]], "Victim": [], "Weapon": []}], "docid": "30050"}