{
  "doctext": "official sources today reported that at least eight people , including soldiers , rebels , and civilians , were killed during clashes between the army and guerrillas over the past weekend in various points of the country . military spoke ##sm ##en for the 6th infantry brigade , headquartered in the eastern us ##ulu ##tan department , told ac ##an - e ##fe that two rebels were killed and one wounded during a clash with government troops in san agustin . meanwhile , the armed forces press committee ( cop ##re ##fa ) reported that the bodies of two guerrillas , who were presumably killed during clashes with the army , were found by soldiers in the outskirts of santa te ##cl ##a , in the central la li ##bert ##ad department . cop ##re ##fa reported that two soldiers were killed during a clash with members of the far ##ab ##und ##o mart ##i national liberation front ( fm ##ln ) in coma ##sa ##gua , about 28 km to the southwest of ( san ) salvador , where a rebel attack on a coffee processing plant was successfully rep ##elled . it reported that a civilian was killed in the cross ##fire and that a soldier was also killed during clashes in zaragoza , south of san salvador , where two guerrillas were wounded . the military report stated that 10 rebels were wounded in te ##col ##uca , san vicente department , about 60 km east of the capital , during an armed clash between insurgents and the 5th ( infantry ) brigade , headquartered in that department . three other soldiers were wounded during an fm ##ln ambush in gu ##az ##apa , north of ( san ) salvador , one of the guerrillas ' main bastion ##s . the salvador ##an ( air ) force this morning bombed rebel positions in the outskirts of ju ##cu ##apa , us ##ulu ##tan department , but no results are yet available , area residents told ac ##an - e ##fe . the fm ##ln this morning ha ##rra ##ssed ( army positions stationed near ) a ##yu ##tu ##xt ##ep ##e ##que , north of ( san ) salvador , without in ##flict ##ing any casualties . cop ##re ##fa also reported that the ( armed ) forces seized from the guerrillas 500 electric cat ##ap ##ult ##s , in the northern ( cha ##late ##nan ##go ) department , which the fm ##ln had used since last year to attack ( san ) salvador garrison ##s . salvador ##an ( red ) cross sources today reported that a 48 - year - old woman identified as maria luz lopez was wounded last night when a powerful bomb , which damaged several businesses in ( san ) salvador , exploded . the bomb was planted in a heavily commercial area of downtown ( san ) salvador causing heavy property loses , according to the owners who provided no specific figures . this is the fourth dynamite attack on businesses in ( san ) salvador so far in 1990 . the guerrillas intensified their acts of sabotage against the economy , especially against the entire electrical power system , on 2 january when an un ##ila ##tera ##l military truce they decreed over the christmas and new year holidays had expired .",
  "pred_seq": "attack [SEP] rebels rebels [SEP] far front [SEP] coffee plant [SEP] [SEP] [SEP] [unused0] attack [SEP] guerrillas guerrillas [SEP] fm ##ln [SEP] coffee plant [SEP] [SEP] [SEP] [unused0] attack [SEP] guerrillas guerrillas [SEP] fm ##ln [SEP] electric electric electric electric [SEP] [SEP] [SEP] [unused0] [CLS]",
  "pred_templates": [
    {
      "incident_type": "attack",
      "PerpInd": [["rebels"]],
      "PerpOrg": [["farabundo marti national liberation front"]],
      "Target": [["coffee processing plant"]],
      "Victim": [],
      "Weapon": []
    },
    {
      "incident_type": "attack",
      "PerpInd": [["guerrillas"]],
      "PerpOrg": [["fmln"]],
      "Target": [["coffee processing plant"]],
      "Victim": [],
      "Weapon": []
    },
    {
      "incident_type": "attack",
      "PerpInd": [["guerrillas"]],
      "PerpOrg": [["fmln"]],
      "Target": [["electric"]],
      "Victim": [],
      "Weapon": []
    }
  ],
  "gold_templates": [
    {
      "incident_type": "attack",
      "PerpInd": [
        [
          "rebel",
          "members of farabundo marti national liberation front fmln",
          "members of farabundo marti national liberation front"
        ]
      ],
      "PerpOrg": [["farabundo marti national liberation front", "fmln"]],
      "Target": [["coffee processing plant"]],
      "Victim": [],
      "Weapon": []
    },
    {
      "incident_type": "attack",
      "PerpInd": [["soldier"], ["guerrillas"]],
      "PerpOrg": [
        ["armed forces"],
        ["farabundo marti national liberation front", "fmln"]
      ],
      "Target": [],
      "Victim": [],
      "Weapon": []
    },
    {
      "incident_type": "bombing",
      "PerpInd": [],
      "PerpOrg": [["farabundo marti national liberation front", "fmln"]],
      "Target": [["businesses"]],
      "Victim": [["maria luz lopez"]],
      "Weapon": [["bomb", "powerful bomb"], ["dynamite"]]
    },
    {
      "incident_type": "attack",
      "PerpInd": [["guerrillas"]],
      "PerpOrg": [["farabundo marti national liberation front", "fmln"]],
      "Target": [["entire electrical power system", "electrical power system"]],
      "Victim": [],
      "Weapon": []
    }
  ],
  "docid": "30080"
}
